pfb_fhir/__init__.py
pfb_fhir/cli.py
pfb_fhir/common.py
pfb_fhir/context_simplifier.py
pfb_fhir/emitter.py
pfb_fhir/gen3_schema_template.yaml
pfb_fhir/handlers.py
pfb_fhir/model.py
pfb_fhir/observable.py
pfb_fhir/terminology/__init__.py
pfb_fhir/terminology/terminology.yaml
pfb_fhir/terminology/value_sets.py
tests/anvil/__init__.py
tests/anvil/conftest.py
tests/anvil/test_emitters.py
tests/anvil/test_model.py
tests/dbgap/__init__.py
tests/dbgap/conftest.py
tests/dbgap/test_dbgap.py
tests/genomics-reporting/__init__.py
tests/genomics-reporting/conftest.py
tests/genomics-reporting/filter.py
tests/genomics-reporting/test_genomics_reporting.py
tests/kf/__init__.py
tests/kf/conftest.py
tests/kf/test_kf.py
tests/ncpi/__init__.py
tests/ncpi/conftest.py
tests/ncpi/test_ncpi.py
tests/simplifier/__init__.py
tests/simplifier/conftest.py
tests/simplifier/test_flattened_simplifier.py
tests/synthea/__init__.py
tests/synthea/conftest.py
tests/synthea/filter.py
tests/synthea/test_synthea.py
tests/terminology/__init__.py
tests/terminology/conftest.py
tests/terminology/test_valuesets.py
pfb_fhir-0.0.8.dist-info/LICENSE
pfb_fhir-0.0.8.dist-info/METADATA
pfb_fhir-0.0.8.dist-info/WHEEL
pfb_fhir-0.0.8.dist-info/entry_points.txt
pfb_fhir-0.0.8.dist-info/top_level.txt
pfb_fhir-0.0.8.dist-info/RECORD
