Metadata-Version: 2.1
Name: pfb-fhir
Version: 0.0.8
Summary: Render a PFB graph from FHIR data
Home-page: https://github.com/bmeg/pfb_fhir
Author: bmeg.io
Author-email: walsbr@ohsu.edu
Project-URL: Bug Reports, https://github.com/bmeg/pfb_fhir/issues
Project-URL: Source, https://github.com/bmeg/pfb_fhir
Keywords: PFB AnVIL terra gen3 bioinformatics fhir
Classifier: Development Status :: 3 - Alpha
Classifier: Intended Audience :: Developers
Classifier: Topic :: Software Development :: Build Tools
Classifier: License :: OSI Approved :: MIT License
Classifier: Programming Language :: Python :: 3.9
Requires-Python: >=3.9, <4
License-File: LICENSE
Requires-Dist: click-loglevel (==0.4.0.post1)
Requires-Dist: tabulate (==0.8.9)
Requires-Dist: requests (==2.27.1)
Requires-Dist: setuptools (==62.2.0)
Requires-Dist: fhirclientr4
Requires-Dist: pydantic (~=1.9.0)
Requires-Dist: pydantic-yaml
Requires-Dist: pytest (==7.1.2)
Requires-Dist: inflection (~=0.5.1)
Requires-Dist: networkx (==2.5)
Requires-Dist: PyYAML (==5.4.1)
Requires-Dist: click (==7.1.2)
Requires-Dist: importlib-metadata (<2.0.0)
Requires-Dist: fastavro (<=1.4.1)
Requires-Dist: pypfb (==0.5.18)
Requires-Dist: dictionaryutils (==3.4.4)
Requires-Dist: matplotlib (==3.5.2)
Requires-Dist: flatten-json (==0.1.13)
